swimlane_vsphere/__init__.py
swimlane_vsphere/__main__.py
swimlane_vsphere/py.typed
swimlane_vsphere/swimlane_vsphere.py
swimlane_vsphere-0.0.5.dist-info/entry_points.txt
swimlane_vsphere-0.0.5.dist-info/LICENSE
swimlane_vsphere-0.0.5.dist-info/WHEEL
swimlane_vsphere-0.0.5.dist-info/METADATA
swimlane_vsphere-0.0.5.dist-info/RECORD
