Metadata-Version: 2.1
Name: swimlane-vsphere
Version: 0.0.5
Summary: Swimlane Vsphere
Home-page: https://github.com/MSAdministrator/swimlane-vsphere
License: MIT
Author: Josh Rickard
Author-email: josh.rickard@swimlane.com
Requires-Python: >=3.7,<4.0
Classifier: Development Status :: 2 - Pre-Alpha
Classifier: License :: OSI Approved :: MIT License
Classifier: Programming Language :: Python :: 3
Classifier: Programming Language :: Python :: 3.10
Classifier: Programming Language :: Python :: 3.7
Classifier: Programming Language :: Python :: 3.8
Classifier: Programming Language :: Python :: 3.9
Requires-Dist: click (>=8.0.1)
Requires-Dist: fire (>=0.4.0,<0.5.0)
Project-URL: Changelog, https://github.com/MSAdministrator/swimlane-vsphere/releases
Project-URL: Documentation, https://swimlane-vsphere.readthedocs.io
Project-URL: Repository, https://github.com/MSAdministrator/swimlane-vsphere
